[{"referee_name":"T Reeves","league":null,"matches":3,"avg_yellows":2.67,"avg_reds":0.33,"avg_fouls":18.3,"over_3_5_cards_pct":null,"over_4_5_cards_pct":0.0,"profile":"LENIENT","card_impact":null,"card_per_foul":null,"volatility":null,"adj_profile":null,"trigger_tag":null}, {"referee_name":"P Tierney","league":null,"matches":3,"avg_yellows":1.33,"avg_reds":0.00,"avg_fouls":18.3,"over_3_5_cards_pct":null,"over_4_5_cards_pct":0.0,"profile":"LENIENT","card_impact":null,"card_per_foul":null,"volatility":null,"adj_profile":null,"trigger_tag":null}, {"referee_name":"S Allison","league":null,"matches":4,"avg_yellows":2.75,"avg_reds":0.00,"avg_fouls":23.3,"over_3_5_cards_pct":null,"over_4_5_cards_pct":0.0,"profile":"LENIENT","card_impact":null,"card_per_foul":null,"volatility":null,"adj_profile":null,"trigger_tag":null}, {"referee_name":"E Duckworth","league":null,"matches":3,"avg_yellows":6.00,"avg_reds":0.00,"avg_fouls":20.3,"over_3_5_cards_pct":null,"over_4_5_cards_pct":66.7,"profile":"STRICT","card_impact":null,"card_per_foul":null,"volatility":null,"adj_profile":null,"trigger_tag":null}, {"referee_name":"B Speedie","league":null,"matches":4,"avg_yellows":1.50,"avg_reds":0.25,"avg_fouls":19.0,"over_3_5_cards_pct":null,"over_4_5_cards_pct":0.0,"profile":"LENIENT","card_impact":null,"card_per_foul":null,"volatility":null,"adj_profile":null,"trigger_tag":null}, {"referee_name":"J Busby","league":null,"matches":6,"avg_yellows":5.67,"avg_reds":0.17,"avg_fouls":22.8,"over_3_5_cards_pct":null,"over_4_5_cards_pct":83.3,"profile":"STRICT","card_impact":2.11,"card_per_foul":24.82,"volatility":1.71,"adj_profile":"CARD_HAPPY","trigger_tag":"TRIGGER_HAPPY"}, {"referee_name":"T Robinson","league":null,"matches":5,"avg_yellows":6.00,"avg_reds":0.20,"avg_fouls":23.4,"over_3_5_cards_pct":null,"over_4_5_cards_pct":60.0,"profile":"STRICT","card_impact":2.10,"card_per_foul":25.64,"volatility":2.18,"adj_profile":"CARD_HAPPY","trigger_tag":"TRIGGER_HAPPY"}, {"referee_name":"S Barrott","league":null,"matches":8,"avg_yellows":4.75,"avg_reds":0.13,"avg_fouls":21.4,"over_3_5_cards_pct":null,"over_4_5_cards_pct":50.0,"profile":"STRICT","card_impact":1.20,"card_per_foul":22.22,"volatility":1.65,"adj_profile":"CARD_HAPPY","trigger_tag":"TRIGGER_HAPPY"}, {"referee_name":"L Doughty","league":null,"matches":7,"avg_yellows":4.71,"avg_reds":0.29,"avg_fouls":23.3,"over_3_5_cards_pct":null,"over_4_5_cards_pct":57.1,"profile":"STRICT","card_impact":1.05,"card_per_foul":20.25,"volatility":2.15,"adj_profile":"CARD_HAPPY","trigger_tag":"TRIGGER_HAPPY"}, {"referee_name":"A Herczeg","league":null,"matches":9,"avg_yellows":4.67,"avg_reds":0.11,"avg_fouls":22.7,"over_3_5_cards_pct":null,"over_4_5_cards_pct":55.6,"profile":"STRICT","card_impact":1.04,"card_per_foul":20.59,"volatility":1.73,"adj_profile":"CARD_HAPPY","trigger_tag":"TRIGGER_HAPPY"}, {"referee_name":"S Attwell","league":null,"matches":10,"avg_yellows":4.60,"avg_reds":0.00,"avg_fouls":21.1,"over_3_5_cards_pct":null,"over_4_5_cards_pct":70.0,"profile":"STRICT","card_impact":1.03,"card_per_foul":21.80,"volatility":1.29,"adj_profile":"CARD_HAPPY","trigger_tag":"TRIGGER_HAPPY"}, {"referee_name":"R Ricardo","league":null,"matches":7,"avg_yellows":4.43,"avg_reds":0.14,"avg_fouls":19.7,"over_3_5_cards_pct":null,"over_4_5_cards_pct":28.6,"profile":"FIRM","card_impact":0.94,"card_per_foul":22.46,"volatility":1.92,"adj_profile":"STRICT_ADJUSTED","trigger_tag":"TRIGGER_HAPPY"}, {"referee_name":"S Hooper","league":null,"matches":8,"avg_yellows":4.75,"avg_reds":0.25,"avg_fouls":25.1,"over_3_5_cards_pct":null,"over_4_5_cards_pct":75.0,"profile":"STRICT","card_impact":0.88,"card_per_foul":18.91,"volatility":2.31,"adj_profile":"STRICT_ADJUSTED","trigger_tag":"NORMAL"}, {"referee_name":"P Bankes","league":null,"matches":10,"avg_yellows":4.20,"avg_reds":0.20,"avg_fouls":24.6,"over_3_5_cards_pct":null,"over_4_5_cards_pct":50.0,"profile":"FIRM","card_impact":0.76,"card_per_foul":17.07,"volatility":1.22,"adj_profile":"STRICT_ADJUSTED","trigger_tag":"NORMAL"}, {"referee_name":"T Nield","league":null,"matches":8,"avg_yellows":4.38,"avg_reds":0.00,"avg_fouls":26.1,"over_3_5_cards_pct":null,"over_4_5_cards_pct":50.0,"profile":"FIRM","card_impact":0.66,"card_per_foul":16.75,"volatility":2.49,"adj_profile":"STRICT_ADJUSTED","trigger_tag":"NORMAL"}, {"referee_name":"B Toner","league":null,"matches":6,"avg_yellows":4.17,"avg_reds":0.17,"avg_fouls":23.7,"over_3_5_cards_pct":null,"over_4_5_cards_pct":33.3,"profile":"FIRM","card_impact":0.66,"card_per_foul":17.61,"volatility":1.52,"adj_profile":"STRICT_ADJUSTED","trigger_tag":"NORMAL"}, {"referee_name":"L Smith","league":null,"matches":9,"avg_yellows":4.22,"avg_reds":0.00,"avg_fouls":18.3,"over_3_5_cards_pct":null,"over_4_5_cards_pct":22.2,"profile":"FIRM","card_impact":0.56,"card_per_foul":23.03,"volatility":1.61,"adj_profile":"STRICT_ADJUSTED","trigger_tag":"TRIGGER_HAPPY"}, {"referee_name":"S Martin","league":null,"matches":7,"avg_yellows":4.43,"avg_reds":0.00,"avg_fouls":22.6,"over_3_5_cards_pct":null,"over_4_5_cards_pct":42.9,"profile":"FIRM","card_impact":0.49,"card_per_foul":19.62,"volatility":2.26,"adj_profile":"STRICT_ADJUSTED","trigger_tag":"NORMAL"}, {"referee_name":"J Brooks","league":null,"matches":5,"avg_yellows":3.80,"avg_reds":0.20,"avg_fouls":28.6,"over_3_5_cards_pct":null,"over_4_5_cards_pct":20.0,"profile":"FIRM","card_impact":0.41,"card_per_foul":13.29,"volatility":1.13,"adj_profile":"STRICT_ADJUSTED","trigger_tag":"NORMAL"}, {"referee_name":"J Bell","league":null,"matches":6,"avg_yellows":4.17,"avg_reds":0.00,"avg_fouls":22.7,"over_3_5_cards_pct":null,"over_4_5_cards_pct":33.3,"profile":"FIRM","card_impact":0.41,"card_per_foul":18.38,"volatility":0.87,"adj_profile":"STRICT_ADJUSTED","trigger_tag":"NORMAL"}, {"referee_name":"F Hallam","league":null,"matches":9,"avg_yellows":3.89,"avg_reds":0.00,"avg_fouls":23.4,"over_3_5_cards_pct":null,"over_4_5_cards_pct":44.4,"profile":"FIRM","card_impact":0.41,"card_per_foul":16.59,"volatility":2.53,"adj_profile":"STRICT_ADJUSTED","trigger_tag":"NORMAL"}, {"referee_name":"A Backhouse","league":null,"matches":10,"avg_yellows":4.20,"avg_reds":0.00,"avg_fouls":21.5,"over_3_5_cards_pct":null,"over_4_5_cards_pct":30.0,"profile":"FIRM","card_impact":0.36,"card_per_foul":19.53,"volatility":1.73,"adj_profile":"STRICT_ADJUSTED","trigger_tag":"NORMAL"}, {"referee_name":"C Kavanagh","league":null,"matches":11,"avg_yellows":3.91,"avg_reds":0.09,"avg_fouls":23.2,"over_3_5_cards_pct":null,"over_4_5_cards_pct":27.3,"profile":"FIRM","card_impact":0.33,"card_per_foul":16.86,"volatility":1.37,"adj_profile":"STRICT_ADJUSTED","trigger_tag":"NORMAL"}, {"referee_name":"M Donohue","league":null,"matches":10,"avg_yellows":3.80,"avg_reds":0.10,"avg_fouls":24.2,"over_3_5_cards_pct":null,"over_4_5_cards_pct":40.0,"profile":"FIRM","card_impact":0.12,"card_per_foul":15.70,"volatility":2.72,"adj_profile":"FAIR","trigger_tag":"NORMAL"}, {"referee_name":"R Madley","league":null,"matches":8,"avg_yellows":3.75,"avg_reds":0.25,"avg_fouls":19.5,"over_3_5_cards_pct":null,"over_4_5_cards_pct":37.5,"profile":"BALANCED","card_impact":0.05,"card_per_foul":19.23,"volatility":1.56,"adj_profile":"FAIR","trigger_tag":"NORMAL"}, {"referee_name":"D England","league":null,"matches":9,"avg_yellows":3.56,"avg_reds":0.11,"avg_fouls":21.3,"over_3_5_cards_pct":null,"over_4_5_cards_pct":44.4,"profile":"BALANCED","card_impact":-0.02,"card_per_foul":16.67,"volatility":1.45,"adj_profile":"FAIR","trigger_tag":"NORMAL"}, {"referee_name":"M Salisbury","league":null,"matches":8,"avg_yellows":3.88,"avg_reds":0.13,"avg_fouls":23.0,"over_3_5_cards_pct":null,"over_4_5_cards_pct":37.5,"profile":"FIRM","card_impact":-0.02,"card_per_foul":16.85,"volatility":1.19,"adj_profile":"FAIR","trigger_tag":"NORMAL"}, {"referee_name":"J Gillett","league":null,"matches":8,"avg_yellows":3.63,"avg_reds":0.13,"avg_fouls":20.5,"over_3_5_cards_pct":null,"over_4_5_cards_pct":37.5,"profile":"BALANCED","card_impact":-0.08,"card_per_foul":17.68,"volatility":1.45,"adj_profile":"FAIR","trigger_tag":"NORMAL"}, {"referee_name":"O Langford","league":null,"matches":7,"avg_yellows":3.86,"avg_reds":0.00,"avg_fouls":21.4,"over_3_5_cards_pct":null,"over_4_5_cards_pct":28.6,"profile":"FIRM","card_impact":-0.09,"card_per_foul":18.00,"volatility":1.32,"adj_profile":"FAIR","trigger_tag":"NORMAL"}, {"referee_name":"T Kirk","league":null,"matches":9,"avg_yellows":3.56,"avg_reds":0.11,"avg_fouls":20.7,"over_3_5_cards_pct":null,"over_4_5_cards_pct":11.1,"profile":"BALANCED","card_impact":-0.10,"card_per_foul":17.20,"volatility":1.23,"adj_profile":"FAIR","trigger_tag":"NORMAL"}, {"referee_name":"D Whitestone","league":null,"matches":8,"avg_yellows":3.38,"avg_reds":0.13,"avg_fouls":24.3,"over_3_5_cards_pct":null,"over_4_5_cards_pct":25.0,"profile":"BALANCED","card_impact":-0.16,"card_per_foul":13.92,"volatility":1.06,"adj_profile":"FAIR","trigger_tag":"NORMAL"}, {"referee_name":"E Bell","league":null,"matches":5,"avg_yellows":3.60,"avg_reds":0.20,"avg_fouls":21.8,"over_3_5_cards_pct":null,"over_4_5_cards_pct":0.0,"profile":"BALANCED","card_impact":-0.24,"card_per_foul":16.51,"volatility":0.88,"adj_profile":"FAIR","trigger_tag":"NORMAL"}, {"referee_name":"A Taylor","league":null,"matches":11,"avg_yellows":3.45,"avg_reds":0.09,"avg_fouls":19.4,"over_3_5_cards_pct":null,"over_4_5_cards_pct":36.4,"profile":"BALANCED","card_impact":-0.25,"card_per_foul":17.84,"volatility":2.18,"adj_profile":"FAIR","trigger_tag":"NORMAL"}, {"referee_name":"A Kitchen","league":null,"matches":10,"avg_yellows":3.30,"avg_reds":0.00,"avg_fouls":24.3,"over_3_5_cards_pct":null,"over_4_5_cards_pct":10.0,"profile":"BALANCED","card_impact":-0.35,"card_per_foul":13.58,"volatility":1.25,"adj_profile":"LENIENT_ADJUSTED","trigger_tag":"NORMAL"}, {"referee_name":"R Jones","league":null,"matches":9,"avg_yellows":2.89,"avg_reds":0.00,"avg_fouls":21.9,"over_3_5_cards_pct":null,"over_4_5_cards_pct":22.2,"profile":"LENIENT","card_impact":-0.46,"card_per_foul":13.20,"volatility":2.19,"adj_profile":"LENIENT_ADJUSTED","trigger_tag":"NORMAL"}, {"referee_name":"T Bramall","league":null,"matches":9,"avg_yellows":3.33,"avg_reds":0.11,"avg_fouls":20.0,"over_3_5_cards_pct":null,"over_4_5_cards_pct":44.4,"profile":"BALANCED","card_impact":-0.47,"card_per_foul":16.67,"volatility":1.44,"adj_profile":"LENIENT_ADJUSTED","trigger_tag":"NORMAL"}, {"referee_name":"A Madley","league":null,"matches":6,"avg_yellows":3.17,"avg_reds":0.00,"avg_fouls":22.3,"over_3_5_cards_pct":null,"over_4_5_cards_pct":16.7,"profile":"BALANCED","card_impact":-0.52,"card_per_foul":14.18,"volatility":1.18,"adj_profile":"LENIENT_ADJUSTED","trigger_tag":"NORMAL"}, {"referee_name":"T Harrington","league":null,"matches":9,"avg_yellows":3.00,"avg_reds":0.22,"avg_fouls":19.0,"over_3_5_cards_pct":null,"over_4_5_cards_pct":22.2,"profile":"LENIENT","card_impact":-0.61,"card_per_foul":15.79,"volatility":1.78,"adj_profile":"LENIENT_ADJUSTED","trigger_tag":"NORMAL"}, {"referee_name":"J Linington","league":null,"matches":6,"avg_yellows":2.67,"avg_reds":0.00,"avg_fouls":18.0,"over_3_5_cards_pct":null,"over_4_5_cards_pct":16.7,"profile":"LENIENT","card_impact":-1.12,"card_per_foul":14.81,"volatility":1.59,"adj_profile":"VERY_LENIENT","trigger_tag":"NORMAL"}, {"referee_name":"J Smith","league":null,"matches":8,"avg_yellows":2.63,"avg_reds":0.13,"avg_fouls":20.9,"over_3_5_cards_pct":null,"over_4_5_cards_pct":12.5,"profile":"LENIENT","card_impact":-1.20,"card_per_foul":12.57,"volatility":1.71,"adj_profile":"VERY_LENIENT","trigger_tag":"NORMAL"}, {"referee_name":"D Webb","league":null,"matches":10,"avg_yellows":2.40,"avg_reds":0.00,"avg_fouls":16.8,"over_3_5_cards_pct":null,"over_4_5_cards_pct":0.0,"profile":"LENIENT","card_impact":-1.23,"card_per_foul":14.29,"volatility":1.16,"adj_profile":"VERY_LENIENT","trigger_tag":"NORMAL"}, {"referee_name":"G Ward","league":null,"matches":9,"avg_yellows":2.67,"avg_reds":0.11,"avg_fouls":19.4,"over_3_5_cards_pct":null,"over_4_5_cards_pct":11.1,"profile":"LENIENT","card_impact":-1.30,"card_per_foul":13.71,"volatility":2.23,"adj_profile":"VERY_LENIENT","trigger_tag":"NORMAL"}, {"referee_name":"M Oliver","league":null,"matches":11,"avg_yellows":2.36,"avg_reds":0.00,"avg_fouls":21.9,"over_3_5_cards_pct":null,"over_4_5_cards_pct":18.2,"profile":"LENIENT","card_impact":-1.40,"card_per_foul":10.79,"volatility":1.81,"adj_profile":"VERY_LENIENT","trigger_tag":"TOLERANT"}, {"referee_name":"C Pawson","league":null,"matches":9,"avg_yellows":1.78,"avg_reds":0.11,"avg_fouls":21.1,"over_3_5_cards_pct":null,"over_4_5_cards_pct":0.0,"profile":"LENIENT","card_impact":-1.59,"card_per_foul":8.42,"volatility":1.39,"adj_profile":"VERY_LENIENT","trigger_tag":"TOLERANT"}]
